{
  "Captain Dreadbeard": {
    "states": {
      "idle": {
        "behaviors": [
          {
            "type": "Wander",
            "speed": 0.4
          }
        ],
        "transitions": []
      }
    },
    "initialState": "idle"
  },
  "Pirate Cutthroat": {
    "states": {
      "idle": {
        "behaviors": [
          {
            "type": "Wander",
            "speed": 0.4
          }
        ],
        "transitions": []
      }
    },
    "initialState": "idle"
  },
  "Pirate Cannoneer": {
    "states": {
      "idle": {
        "behaviors": [
          {
            "type": "Wander",
            "speed": 0.4
          }
        ],
        "transitions": []
      }
    },
    "initialState": "idle"
  },
  "Dreadbeard's Parrot": {
    "states": {
      "idle": {
        "behaviors": [
          {
            "type": "Wander",
            "speed": 0.4
          }
        ],
        "transitions": []
      }
    },
    "initialState": "idle"
  }
}